cloudlet.py
cloudlet-1.2.0.dist-info/licenses/LICENSE
cloudlet-1.2.0.dist-info/METADATA
cloudlet-1.2.0.dist-info/WHEEL
cloudlet-1.2.0.dist-info/entry_points.txt
cloudlet-1.2.0.dist-info/top_level.txt
cloudlet-1.2.0.dist-info/RECORD
