Metadata-Version: 2.4
Name: Cloudlet
Version: 1.2.0
Summary: A Python file server with web ui with roles, based on Flask
Home-page: https://github.com/ByteBendr/cloudlet
Author: Lucian
Author-email: lucianclaudiu73@gmail.com
Classifier: Programming Language :: Python :: 3
Classifier: License :: OSI Approved :: MIT License
Classifier: Operating System :: OS Independent
Requires-Python: >=3.7
License-File: LICENSE
Requires-Dist: Flask>=2.0
Dynamic: author
Dynamic: author-email
Dynamic: classifier
Dynamic: description
Dynamic: description-content-type
Dynamic: home-page
Dynamic: license-file
Dynamic: requires-dist
Dynamic: requires-python
Dynamic: summary
